pomotime/__init__.py
pomotime/__main__.py
pomotime/pomotime.py
pomotime/sound.wav
pomotime/config/pomotime.toml
pomotime/sounds/1.mp3
pomotime-1.0.2.dist-info/LICENSE
pomotime-1.0.2.dist-info/METADATA
pomotime-1.0.2.dist-info/WHEEL
pomotime-1.0.2.dist-info/entry_points.txt
pomotime-1.0.2.dist-info/top_level.txt
pomotime-1.0.2.dist-info/RECORD
