Metadata-Version: 2.1
Name: pomotime
Version: 1.0.2
Summary: Stylish customizable CLI Pomodoro timer
Home-page: https://github.com/zabojeb/pomotime
Author: zabojeb
Author-email: zabojeb@bk.ru
Classifier: Programming Language :: Python :: 3
Classifier: License :: OSI Approved :: Apache Software License
Classifier: Operating System :: OS Independent
Requires-Python: >=3.0
License-File: LICENSE
Requires-Dist: Click
Requires-Dist: rich
Requires-Dist: art
Requires-Dist: appdirs
Requires-Dist: toml
